<?xml version="1.0" encoding="utf-8"?>
<video FPS="30" filename="video_0142.mp4" id="video_0142" length_sec="10" num_frames="300">
   <tags>
      <time_of_day val="daytime"/>
      <weather val="cloudy"/>
      <location val="street"/>
   </tags>
   <subjects>
      <Driver/>
      <car/>
   </subjects>
   <actions>
      <Driver>
         <action end_frame="14" end_time="0.46667" id="moving fast" start_frame="1" start_time="0"/>
         <action end_frame="46" end_time="1.5333" id="accelerating" start_frame="15" start_time="0.5"/>
         <action end_frame="149" end_time="4.9667" id="decelerating" start_frame="47" start_time="1.5667"/>
         <action end_frame="300" end_time="10" id="accelerating" start_frame="150" start_time="5"/>
      </Driver>
   </actions>
</video>