<annotations><version>1.1</version><meta><task><id>1</id><name>video_0195</name><size>90</size><mode>interpolation</mode><overlap>5</overlap><bugtracker /><flipped>False</flipped><created>2019-02-18 20:02:59.930671+03:00</created><updated>2019-02-18 20:02:59.930671+03:00</updated><source>data/video_0195.mp4</source><labels><label><name>pedestrian</name><attributes><attribute>@text=id:</attribute><attribute>@text=old_id:</attribute><attribute>~select=action:standing,walking</attribute><attribute>~select=nod:__undefined__,nodding</attribute><attribute>~select=look:not-looking,looking</attribute><attribute>~select=hand_gesture:__undefined__,greet,yield,rightofway,other</attribute><attribute>~select=reaction:__undefined__,clear_path,speed_up,slow_down</attribute><attribute>~select=cross:not-crossing,crossing</attribute><attribute>~select=occlusion:none,part,full</attribute></attributes></label><label><name>ped</name><attributes><attribute>@text=id:</attribute><attribute>@text=old_id:</attribute><attribute>~select=occlusion:none,part,full</attribute></attributes></label><label><name>people</name><attributes><attribute>@text=id:</attribute><attribute>@text=old_id:</attribute><attribute>~select=occlusion:none,part,full</attribute></attributes></label></labels><segments><segment><id>1</id><start>0</start><stop>89</stop><url>http://localhost:8080/?id=206</url></segment></segments><owner><username>aras</username><email>aras@eecs.yorku.ca</email></owner><original_size><width>1920</width><height>1080</height></original_size><video_attributes><time_of_day>daytime</time_of_day><weather>clear</weather><location>street</location></video_attributes></task><dumped>2019-02-18 20:02:59.930671+03:00</dumped></meta><track label="ped"><box frame="0" keyframe="1" occluded="1" outside="0" xbr="430.0" xtl="398.0" ybr="673.0" ytl="599.0"><attribute name="id">0_195_1434</attribute><attribute name="old_id">ped5</attribute><attribute name="occlusion">part</attribute></box><box frame="1" keyframe="1" occluded="1" outside="0" xbr="430.0" xtl="398.0" ybr="673.0" ytl="599.0"><attribute name="id">0_195_1434</attribute><attribute name="old_id">ped5</attribute><attribute name="occlusion">part</attribute></box><box frame="2" keyframe="1" occluded="1" outside="0" xbr="429.0" xtl="397.0" ybr="674.0" ytl="600.0"><attribute name="id">0_195_1434</attribute><attribute name="old_id">ped5</attribute><attribute name="occlusion">part</attribute></box><box frame="3" keyframe="1" occluded="1" outside="0" xbr="428.0" xtl="396.0" ybr="674.0" ytl="600.0"><attribute name="id">0_195_1434</attribute><attribute name="old_id">ped5</attribute><attribute name="occlusion">part</attribute></box><box frame="4" keyframe="1" occluded="1" outside="0" xbr="428.0" xtl="396.0" ybr="675.0" ytl="601.0"><attribute name="id">0_195_1434</attribute><attribute name="old_id">ped5</attribute><attribute name="occlusion">part</attribute></box><box frame="5" keyframe="1" occluded="1" outside="0" xbr="427.0" xtl="395.0" ybr="675.0" ytl="601.0"><attribute name="id">0_195_1434</attribute><attribute name="old_id">ped5</attribute><attribute name="occlusion">part</attribute></box><box frame="6" keyframe="1" occluded="1" outside="0" xbr="426.0" xtl="394.0" ybr="676.0" ytl="602.0"><attribute name="id">0_195_1434</attribute><attribute name="old_id">ped5</attribute><attribute name="occlusion">part</attribute></box><box frame="7" keyframe="1" occluded="1" outside="0" xbr="426.0" xtl="394.0" ybr="675.0" ytl="602.0"><attribute name="id">0_195_1434</attribute><attribute name="old_id">ped5</attribute><attribute name="occlusion">part</attribute></box><box frame="8" keyframe="1" occluded="1" outside="0" xbr="425.0" xtl="393.0" ybr="676.0" ytl="603.0"><attribute name="id">0_195_1434</attribute><attribute name="old_id">ped5</attribute><attribute name="occlusion">part</attribute></box><box frame="9" keyframe="1" occluded="1" outside="0" xbr="424.0" xtl="392.0" ybr="676.0" ytl="603.0"><attribute name="id">0_195_1434</attribute><attribute name="old_id">ped5</attribute><attribute name="occlusion">part</attribute></box><box frame="10" keyframe="1" occluded="1" outside="0" xbr="423.0" xtl="391.0" ybr="677.0" ytl="604.0"><attribute name="id">0_195_1434</attribute><attribute name="old_id">ped5</attribute><attribute name="occlusion">part</attribute></box><box frame="11" keyframe="1" occluded="1" outside="0" xbr="423.0" xtl="391.0" ybr="678.0" ytl="605.0"><attribute name="id">0_195_1434</attribute><attribute name="old_id">ped5</attribute><attribute name="occlusion">part</attribute></box><box frame="12" keyframe="1" occluded="1" outside="0" xbr="422.0" xtl="390.0" ybr="678.0" ytl="605.0"><attribute name="id">0_195_1434</attribute><attribute name="old_id">ped5</attribute><attribute name="occlusion">part</attribute></box><box frame="13" keyframe="1" occluded="1" outside="0" xbr="421.0" xtl="389.0" ybr="679.0" ytl="606.0"><attribute name="id">0_195_1434</attribute><attribute name="old_id">ped5</attribute><attribute name="occlusion">part</attribute></box><box frame="14" keyframe="1" occluded="1" outside="0" xbr="421.0" xtl="389.0" ybr="679.0" ytl="606.0"><attribute name="id">0_195_1434</attribute><attribute name="old_id">ped5</attribute><attribute name="occlusion">part</attribute></box><box frame="15" keyframe="1" occluded="1" outside="0" xbr="420.0" xtl="388.0" ybr="680.0" ytl="607.0"><attribute name="id">0_195_1434</attribute><attribute name="old_id">ped5</attribute><attribute name="occlusion">part</attribute></box><box frame="16" keyframe="1" occluded="1" outside="0" xbr="418.0" xtl="387.0" ybr="679.0" ytl="606.0"><attribute name="id">0_195_1434</attribute><attribute name="old_id">ped5</attribute><attribute name="occlusion">part</attribute></box><box frame="17" keyframe="1" occluded="1" outside="0" xbr="418.0" xtl="387.0" ybr="678.0" ytl="605.0"><attribute name="id">0_195_1434</attribute><attribute name="old_id">ped5</attribute><attribute name="occlusion">part</attribute></box><box frame="18" keyframe="1" occluded="1" outside="0" xbr="417.0" xtl="386.0" ybr="678.0" ytl="604.0"><attribute name="id">0_195_1434</attribute><attribute name="old_id">ped5</attribute><attribute name="occlusion">part</attribute></box><box frame="19" keyframe="1" occluded="1" outside="0" xbr="415.0" xtl="385.0" ybr="677.0" ytl="603.0"><attribute name="id">0_195_1434</attribute><attribute name="old_id">ped5</attribute><attribute name="occlusion">part</attribute></box><box frame="20" keyframe="1" occluded="1" outside="0" xbr="414.0" xtl="384.0" ybr="676.0" ytl="602.0"><attribute name="id">0_195_1434</attribute><attribute name="old_id">ped5</attribute><attribute name="occlusion">part</attribute></box><box frame="21" keyframe="1" occluded="1" outside="0" xbr="414.0" xtl="384.0" ybr="676.0" ytl="601.0"><attribute name="id">0_195_1434</attribute><attribute name="old_id">ped5</attribute><attribute name="occlusion">part</attribute></box><box frame="22" keyframe="1" occluded="1" outside="0" xbr="413.0" xtl="383.0" ybr="675.0" ytl="600.0"><attribute name="id">0_195_1434</attribute><attribute name="old_id">ped5</attribute><attribute name="occlusion">part</attribute></box><box frame="23" keyframe="1" occluded="1" outside="0" xbr="411.0" xtl="382.0" ybr="674.0" ytl="599.0"><attribute name="id">0_195_1434</attribute><attribute name="old_id">ped5</attribute><attribute name="occlusion">part</attribute></box><box frame="24" keyframe="1" occluded="1" outside="0" xbr="411.0" xtl="382.0" ybr="673.0" ytl="598.0"><attribute name="id">0_195_1434</attribute><attribute name="old_id">ped5</attribute><attribute name="occlusion">part</attribute></box><box frame="25" keyframe="1" occluded="1" outside="0" xbr="410.0" xtl="381.0" ybr="673.0" ytl="597.0"><attribute name="id">0_195_1434</attribute><attribute name="old_id">ped5</attribute><attribute name="occlusion">part</attribute></box><box frame="26" keyframe="1" occluded="1" outside="0" xbr="408.0" xtl="380.0" ybr="672.0" ytl="596.0"><attribute name="id">0_195_1434</attribute><attribute name="old_id">ped5</attribute><attribute name="occlusion">part</attribute></box><box frame="27" keyframe="1" occluded="1" outside="0" xbr="408.0" xtl="380.0" ybr="671.0" ytl="595.0"><attribute name="id">0_195_1434</attribute><attribute name="old_id">ped5</attribute><attribute name="occlusion">part</attribute></box><box frame="28" keyframe="1" occluded="1" outside="0" xbr="407.0" xtl="379.0" ybr="671.0" ytl="594.0"><attribute name="id">0_195_1434</attribute><attribute name="old_id">ped5</attribute><attribute name="occlusion">full</attribute></box><box frame="29" keyframe="1" occluded="1" outside="0" xbr="406.0" xtl="378.0" ybr="670.0" ytl="593.0"><attribute name="id">0_195_1434</attribute><attribute name="old_id">ped5</attribute><attribute name="occlusion">full</attribute></box><box frame="30" keyframe="1" occluded="1" outside="0" xbr="404.0" xtl="377.0" ybr="669.0" ytl="592.0"><attribute name="id">0_195_1434</attribute><attribute name="old_id">ped5</attribute><attribute name="occlusion">full</attribute></box><box frame="31" keyframe="1" occluded="1" outside="0" xbr="404.0" xtl="377.0" ybr="669.0" ytl="592.0"><attribute name="id">0_195_1434</attribute><attribute name="old_id">ped5</attribute><attribute name="occlusion">full</attribute></box><box frame="32" keyframe="1" occluded="1" outside="0" xbr="404.0" xtl="377.0" ybr="669.0" ytl="592.0"><attribute name="id">0_195_1434</attribute><attribute name="old_id">ped5</attribute><attribute name="occlusion">full</attribute></box><box frame="33" keyframe="1" occluded="1" outside="0" xbr="404.0" xtl="377.0" ybr="669.0" ytl="592.0"><attribute name="id">0_195_1434</attribute><attribute name="old_id">ped5</attribute><attribute name="occlusion">full</attribute></box><box frame="34" keyframe="1" occluded="1" outside="0" xbr="404.0" xtl="377.0" ybr="669.0" ytl="592.0"><attribute name="id">0_195_1434</attribute><attribute name="old_id">ped5</attribute><attribute name="occlusion">full</attribute></box></track><track label="ped"><box frame="47" keyframe="1" occluded="1" outside="0" xbr="1830.0" xtl="1769.0" ybr="713.0" ytl="536.0"><attribute name="id">0_195_1435</attribute><attribute name="old_id">ped4</attribute><attribute name="occlusion">full</attribute></box><box frame="48" keyframe="1" occluded="1" outside="0" xbr="1839.0" xtl="1778.0" ybr="715.0" ytl="534.0"><attribute name="id">0_195_1435</attribute><attribute name="old_id">ped4</attribute><attribute name="occlusion">part</attribute></box><box frame="49" keyframe="1" occluded="1" outside="0" xbr="1848.0" xtl="1788.0" ybr="718.0" ytl="532.0"><attribute name="id">0_195_1435</attribute><attribute name="old_id">ped4</attribute><attribute name="occlusion">part</attribute></box><box frame="50" keyframe="1" occluded="1" outside="0" xbr="1857.0" xtl="1797.0" ybr="721.0" ytl="531.0"><attribute name="id">0_195_1435</attribute><attribute name="old_id">ped4</attribute><attribute name="occlusion">part</attribute></box><box frame="51" keyframe="1" occluded="1" outside="0" xbr="1866.0" xtl="1806.0" ybr="724.0" ytl="529.0"><attribute name="id">0_195_1435</attribute><attribute name="old_id">ped4</attribute><attribute name="occlusion">part</attribute></box><box frame="52" keyframe="1" occluded="1" outside="0" xbr="1876.0" xtl="1816.0" ybr="727.0" ytl="528.0"><attribute name="id">0_195_1435</attribute><attribute name="old_id">ped4</attribute><attribute name="occlusion">part</attribute></box><box frame="53" keyframe="1" occluded="1" outside="0" xbr="1884.0" xtl="1825.0" ybr="730.0" ytl="526.0"><attribute name="id">0_195_1435</attribute><attribute name="old_id">ped4</attribute><attribute name="occlusion">part</attribute></box><box frame="54" keyframe="1" occluded="0" outside="0" xbr="1893.0" xtl="1834.0" ybr="733.0" ytl="525.0"><attribute name="id">0_195_1435</attribute><attribute name="old_id">ped4</attribute><attribute name="occlusion">none</attribute></box><box frame="55" keyframe="1" occluded="0" outside="0" xbr="1897.0" xtl="1844.0" ybr="735.0" ytl="525.0"><attribute name="id">0_195_1435</attribute><attribute name="old_id">ped4</attribute><attribute name="occlusion">none</attribute></box><box frame="56" keyframe="1" occluded="0" outside="0" xbr="1902.0" xtl="1855.0" ybr="737.0" ytl="525.0"><attribute name="id">0_195_1435</attribute><attribute name="old_id">ped4</attribute><attribute name="occlusion">none</attribute></box><box frame="57" keyframe="1" occluded="0" outside="0" xbr="1917.0" xtl="1865.0" ybr="752.0" ytl="525.0"><attribute name="id">0_195_1435</attribute><attribute name="old_id">ped4</attribute><attribute name="occlusion">none</attribute></box><box frame="58" keyframe="1" occluded="0" outside="0" xbr="1917.0" xtl="1875.0" ybr="750.0" ytl="525.0"><attribute name="id">0_195_1435</attribute><attribute name="old_id">ped4</attribute><attribute name="occlusion">none</attribute></box><box frame="59" keyframe="1" occluded="1" outside="0" xbr="1918.0" xtl="1885.0" ybr="747.0" ytl="525.0"><attribute name="id">0_195_1435</attribute><attribute name="old_id">ped4</attribute><attribute name="occlusion">part</attribute></box><box frame="60" keyframe="1" occluded="1" outside="0" xbr="1919.0" xtl="1895.0" ybr="744.0" ytl="525.0"><attribute name="id">0_195_1435</attribute><attribute name="old_id">ped4</attribute><attribute name="occlusion">full</attribute></box></track><track label="ped"><box frame="5" keyframe="1" occluded="1" outside="0" xbr="71.0" xtl="7.0" ybr="927.0" ytl="585.0"><attribute name="id">0_195_1436</attribute><attribute name="old_id">ped2</attribute><attribute name="occlusion">part</attribute></box><box frame="6" keyframe="1" occluded="1" outside="0" xbr="59.0" xtl="3.0" ybr="917.0" ytl="591.0"><attribute name="id">0_195_1436</attribute><attribute name="old_id">ped2</attribute><attribute name="occlusion">full</attribute></box><box frame="7" keyframe="1" occluded="1" outside="0" xbr="32.0" xtl="1.0" ybr="927.0" ytl="596.0"><attribute name="id">0_195_1436</attribute><attribute name="old_id">ped2</attribute><attribute name="occlusion">full</attribute></box></track><track label="pedestrian"><box frame="0" keyframe="1" occluded="0" outside="0" xbr="1099.0" xtl="1040.0" ybr="733.0" ytl="563.0"><attribute name="id">0_195_1436b</attribute><attribute name="old_id">pedestrian</attribute><attribute name="look">looking</attribute><attribute name="reaction">__undefined__</attribute><attribute name="action">standing</attribute><attribute name="cross">not-crossing</attribute><attribute name="hand_gesture">__undefined__</attribute><attribute name="occlusion">none</attribute><attribute name="nod">__undefined__</attribute></box><box frame="1" keyframe="1" occluded="0" outside="0" xbr="1105.0" xtl="1044.0" ybr="735.0" ytl="563.0"><attribute name="id">0_195_1436b</attribute><attribute name="old_id">pedestrian</attribute><attribute name="look">looking</attribute><attribute name="reaction">__undefined__</attribute><attribute name="action">standing</attribute><attribute name="cross">not-crossing</attribute><attribute name="hand_gesture">__undefined__</attribute><attribute name="occlusion">none</attribute><attribute name="nod">__undefined__</attribute></box><box frame="2" keyframe="1" occluded="0" outside="0" xbr="1111.0" xtl="1047.0" ybr="736.0" ytl="562.0"><attribute name="id">0_195_1436b</attribute><attribute name="old_id">pedestrian</attribute><attribute name="look">looking</attribute><attribute name="reaction">__undefined__</attribute><attribute name="action">standing</attribute><attribute name="cross">not-crossing</attribute><attribute name="hand_gesture">__undefined__</attribute><attribute name="occlusion">none</attribute><attribute name="nod">__undefined__</attribute></box><box frame="3" keyframe="1" occluded="0" outside="0" xbr="1117.0" xtl="1051.0" ybr="738.0" ytl="562.0"><attribute name="id">0_195_1436b</attribute><attribute name="old_id">pedestrian</attribute><attribute name="look">looking</attribute><attribute name="reaction">__undefined__</attribute><attribute name="action">standing</attribute><attribute name="cross">not-crossing</attribute><attribute name="hand_gesture">__undefined__</attribute><attribute name="occlusion">none</attribute><attribute name="nod">__undefined__</attribute></box><box frame="4" keyframe="1" occluded="0" outside="0" xbr="1122.0" xtl="1053.0" ybr="740.0" ytl="562.0"><attribute name="id">0_195_1436b</attribute><attribute name="old_id">pedestrian</attribute><attribute name="look">looking</attribute><attribute name="reaction">__undefined__</attribute><attribute name="action">standing</attribute><attribute name="cross">not-crossing</attribute><attribute name="hand_gesture">__undefined__</attribute><attribute name="occlusion">none</attribute><attribute name="nod">__undefined__</attribute></box><box frame="5" keyframe="1" occluded="0" outside="0" xbr="1127.0" xtl="1054.0" ybr="742.0" ytl="562.0"><attribute name="id">0_195_1436b</attribute><attribute name="old_id">pedestrian</attribute><attribute name="look">looking</attribute><attribute name="reaction">__undefined__</attribute><attribute name="action">standing</attribute><attribute name="cross">not-crossing</attribute><attribute name="hand_gesture">__undefined__</attribute><attribute name="occlusion">none</attribute><attribute name="nod">__undefined__</attribute></box><box frame="6" keyframe="1" occluded="0" outside="0" xbr="1132.0" xtl="1056.0" ybr="744.0" ytl="562.0"><attribute name="id">0_195_1436b</attribute><attribute name="old_id">pedestrian</attribute><attribute name="look">looking</attribute><attribute name="reaction">__undefined__</attribute><attribute name="action">standing</attribute><attribute name="cross">not-crossing</attribute><attribute name="hand_gesture">__undefined__</attribute><attribute name="occlusion">none</attribute><attribute name="nod">__undefined__</attribute></box><box frame="7" keyframe="1" occluded="0" outside="0" xbr="1137.0" xtl="1060.0" ybr="747.0" ytl="563.0"><attribute name="id">0_195_1436b</attribute><attribute name="old_id">pedestrian</attribute><attribute name="look">looking</attribute><attribute name="reaction">__undefined__</attribute><attribute name="action">standing</attribute><attribute name="cross">not-crossing</attribute><attribute name="hand_gesture">__undefined__</attribute><attribute name="occlusion">none</attribute><attribute name="nod">__undefined__</attribute></box><box frame="8" keyframe="1" occluded="0" outside="0" xbr="1141.0" xtl="1064.0" ybr="748.0" ytl="563.0"><attribute name="id">0_195_1436b</attribute><attribute name="old_id">pedestrian</attribute><attribute name="look">looking</attribute><attribute name="reaction">__undefined__</attribute><attribute name="action">standing</attribute><attribute name="cross">not-crossing</attribute><attribute name="hand_gesture">__undefined__</attribute><attribute name="occlusion">none</attribute><attribute name="nod">__undefined__</attribute></box><box frame="9" keyframe="1" occluded="0" outside="0" xbr="1146.0" xtl="1068.0" ybr="751.0" ytl="564.0"><attribute name="id">0_195_1436b</attribute><attribute name="old_id">pedestrian</attribute><attribute name="look">looking</attribute><attribute name="reaction">__undefined__</attribute><attribute name="action">standing</attribute><attribute name="cross">not-crossing</attribute><attribute name="hand_gesture">__undefined__</attribute><attribute name="occlusion">none</attribute><attribute name="nod">__undefined__</attribute></box><box frame="10" keyframe="1" occluded="0" outside="0" xbr="1150.0" xtl="1073.0" ybr="755.0" ytl="566.0"><attribute name="id">0_195_1436b</attribute><attribute name="old_id">pedestrian</attribute><attribute name="look">looking</attribute><attribute name="reaction">__undefined__</attribute><attribute name="action">standing</attribute><attribute name="cross">not-crossing</attribute><attribute name="hand_gesture">__undefined__</attribute><attribute name="occlusion">none</attribute><attribute name="nod">__undefined__</attribute></box><box frame="11" keyframe="1" occluded="0" outside="0" xbr="1152.0" xtl="1077.0" ybr="757.0" ytl="567.0"><attribute name="id">0_195_1436b</attribute><attribute name="old_id">pedestrian</attribute><attribute name="look">looking</attribute><attribute name="reaction">__undefined__</attribute><attribute name="action">standing</attribute><attribute name="cross">not-crossing</attribute><attribute name="hand_gesture">__undefined__</attribute><attribute name="occlusion">none</attribute><attribute name="nod">__undefined__</attribute></box><box frame="12" keyframe="1" occluded="0" outside="0" xbr="1156.0" xtl="1082.0" ybr="761.0" ytl="569.0"><attribute name="id">0_195_1436b</attribute><attribute name="old_id">pedestrian</attribute><attribute name="look">looking</attribute><attribute name="reaction">__undefined__</attribute><attribute name="action">standing</attribute><attribute name="cross">not-crossing</attribute><attribute name="hand_gesture">__undefined__</attribute><attribute name="occlusion">none</attribute><attribute name="nod">__undefined__</attribute></box><box frame="13" keyframe="1" occluded="0" outside="0" xbr="1160.0" xtl="1086.0" ybr="765.0" ytl="570.0"><attribute name="id">0_195_1436b</attribute><attribute name="old_id">pedestrian</attribute><attribute name="look">looking</attribute><attribute name="reaction">__undefined__</attribute><attribute name="action">standing</attribute><attribute name="cross">not-crossing</attribute><attribute name="hand_gesture">__undefined__</attribute><attribute name="occlusion">none</attribute><attribute name="nod">__undefined__</attribute></box><box frame="14" keyframe="1" occluded="0" outside="0" xbr="1165.0" xtl="1091.0" ybr="768.0" ytl="570.0"><attribute name="id">0_195_1436b</attribute><attribute name="old_id">pedestrian</attribute><attribute name="look">looking</attribute><attribute name="reaction">__undefined__</attribute><attribute name="action">standing</attribute><attribute name="cross">not-crossing</attribute><attribute name="hand_gesture">__undefined__</attribute><attribute name="occlusion">none</attribute><attribute name="nod">__undefined__</attribute></box><box frame="15" keyframe="1" occluded="0" outside="0" xbr="1168.0" xtl="1095.0" ybr="771.0" ytl="571.0"><attribute name="id">0_195_1436b</attribute><attribute name="old_id">pedestrian</attribute><attribute name="look">looking</attribute><attribute name="reaction">__undefined__</attribute><attribute name="action">standing</attribute><attribute name="cross">not-crossing</attribute><attribute name="hand_gesture">__undefined__</attribute><attribute name="occlusion">none</attribute><attribute name="nod">__undefined__</attribute></box><box frame="16" keyframe="1" occluded="0" outside="0" xbr="1172.0" xtl="1099.0" ybr="774.0" ytl="571.0"><attribute name="id">0_195_1436b</attribute><attribute name="old_id">pedestrian</attribute><attribute name="look">looking</attribute><attribute name="reaction">__undefined__</attribute><attribute name="action">standing</attribute><attribute name="cross">not-crossing</attribute><attribute name="hand_gesture">__undefined__</attribute><attribute name="occlusion">none</attribute><attribute name="nod">__undefined__</attribute></box><box frame="17" keyframe="1" occluded="0" outside="0" xbr="1177.0" xtl="1103.0" ybr="776.0" ytl="570.0"><attribute name="id">0_195_1436b</attribute><attribute name="old_id">pedestrian</attribute><attribute name="look">looking</attribute><attribute name="reaction">__undefined__</attribute><attribute name="action">standing</attribute><attribute name="cross">not-crossing</attribute><attribute name="hand_gesture">__undefined__</attribute><attribute name="occlusion">none</attribute><attribute name="nod">__undefined__</attribute></box><box frame="18" keyframe="1" occluded="0" outside="0" xbr="1183.0" xtl="1107.0" ybr="777.0" ytl="568.0"><attribute name="id">0_195_1436b</attribute><attribute name="old_id">pedestrian</attribute><attribute name="look">looking</attribute><attribute name="reaction">__undefined__</attribute><attribute name="action">standing</attribute><attribute name="cross">not-crossing</attribute><attribute name="hand_gesture">__undefined__</attribute><attribute name="occlusion">none</attribute><attribute name="nod">__undefined__</attribute></box><box frame="19" keyframe="1" occluded="0" outside="0" xbr="1189.0" xtl="1112.0" ybr="780.0" ytl="567.0"><attribute name="id">0_195_1436b</attribute><attribute name="old_id">pedestrian</attribute><attribute name="look">looking</attribute><attribute name="reaction">__undefined__</attribute><attribute name="action">standing</attribute><attribute name="cross">not-crossing</attribute><attribute name="hand_gesture">__undefined__</attribute><attribute name="occlusion">none</attribute><attribute name="nod">__undefined__</attribute></box><box frame="20" keyframe="1" occluded="0" outside="0" xbr="1195.0" xtl="1116.0" ybr="781.0" ytl="565.0"><attribute name="id">0_195_1436b</attribute><attribute name="old_id">pedestrian</attribute><attribute name="look">looking</attribute><attribute name="reaction">__undefined__</attribute><attribute name="action">standing</attribute><attribute name="cross">not-crossing</attribute><attribute name="hand_gesture">__undefined__</attribute><attribute name="occlusion">none</attribute><attribute name="nod">__undefined__</attribute></box><box frame="21" keyframe="1" occluded="0" outside="0" xbr="1200.0" xtl="1120.0" ybr="783.0" ytl="564.0"><attribute name="id">0_195_1436b</attribute><attribute name="old_id">pedestrian</attribute><attribute name="look">looking</attribute><attribute name="reaction">__undefined__</attribute><attribute name="action">standing</attribute><attribute name="cross">not-crossing</attribute><attribute name="hand_gesture">__undefined__</attribute><attribute name="occlusion">none</attribute><attribute name="nod">__undefined__</attribute></box><box frame="22" keyframe="1" occluded="0" outside="0" xbr="1205.0" xtl="1125.0" ybr="785.0" ytl="563.0"><attribute name="id">0_195_1436b</attribute><attribute name="old_id">pedestrian</attribute><attribute name="look">looking</attribute><attribute name="reaction">__undefined__</attribute><attribute name="action">standing</attribute><attribute name="cross">not-crossing</attribute><attribute name="hand_gesture">__undefined__</attribute><attribute name="occlusion">none</attribute><attribute name="nod">__undefined__</attribute></box><box frame="23" keyframe="1" occluded="0" outside="0" xbr="1212.0" xtl="1131.0" ybr="787.0" ytl="563.0"><attribute name="id">0_195_1436b</attribute><attribute name="old_id">pedestrian</attribute><attribute name="look">looking</attribute><attribute name="reaction">__undefined__</attribute><attribute name="action">standing</attribute><attribute name="cross">not-crossing</attribute><attribute name="hand_gesture">__undefined__</attribute><attribute name="occlusion">none</attribute><attribute name="nod">__undefined__</attribute></box><box frame="24" keyframe="1" occluded="0" outside="0" xbr="1217.0" xtl="1136.0" ybr="789.0" ytl="562.0"><attribute name="id">0_195_1436b</attribute><attribute name="old_id">pedestrian</attribute><attribute name="look">looking</attribute><attribute name="reaction">__undefined__</attribute><attribute name="action">standing</attribute><attribute name="cross">not-crossing</attribute><attribute name="hand_gesture">__undefined__</attribute><attribute name="occlusion">none</attribute><attribute name="nod">__undefined__</attribute></box><box frame="25" keyframe="1" occluded="0" outside="0" xbr="1222.0" xtl="1141.0" ybr="790.0" ytl="561.0"><attribute name="id">0_195_1436b</attribute><attribute name="old_id">pedestrian</attribute><attribute name="look">looking</attribute><attribute name="reaction">__undefined__</attribute><attribute name="action">standing</attribute><attribute name="cross">not-crossing</attribute><attribute name="hand_gesture">__undefined__</attribute><attribute name="occlusion">none</attribute><attribute name="nod">__undefined__</attribute></box><box frame="26" keyframe="1" occluded="0" outside="0" xbr="1229.0" xtl="1147.0" ybr="793.0" ytl="559.0"><attribute name="id">0_195_1436b</attribute><attribute name="old_id">pedestrian</attribute><attribute name="look">looking</attribute><attribute name="reaction">__undefined__</attribute><attribute name="action">standing</attribute><attribute name="cross">not-crossing</attribute><attribute name="hand_gesture">__undefined__</attribute><attribute name="occlusion">none</attribute><attribute name="nod">__undefined__</attribute></box><box frame="27" keyframe="1" occluded="0" outside="0" xbr="1237.0" xtl="1154.0" ybr="797.0" ytl="557.0"><attribute name="id">0_195_1436b</attribute><attribute name="old_id">pedestrian</attribute><attribute name="look">looking</attribute><attribute name="reaction">__undefined__</attribute><attribute name="action">standing</attribute><attribute name="cross">not-crossing</attribute><attribute name="hand_gesture">__undefined__</attribute><attribute name="occlusion">none</attribute><attribute name="nod">__undefined__</attribute></box><box frame="28" keyframe="1" occluded="0" outside="0" xbr="1244.0" xtl="1160.0" ybr="800.0" ytl="555.0"><attribute name="id">0_195_1436b</attribute><attribute name="old_id">pedestrian</attribute><attribute name="look">looking</attribute><attribute name="reaction">__undefined__</attribute><attribute name="action">standing</attribute><attribute name="cross">not-crossing</attribute><attribute name="hand_gesture">__undefined__</attribute><attribute name="occlusion">none</attribute><attribute name="nod">__undefined__</attribute></box><box frame="29" keyframe="1" occluded="0" outside="0" xbr="1253.0" xtl="1168.0" ybr="802.0" ytl="554.0"><attribute name="id">0_195_1436b</attribute><attribute name="old_id">pedestrian</attribute><attribute name="look">looking</attribute><attribute name="reaction">__undefined__</attribute><attribute name="action">standing</attribute><attribute name="cross">not-crossing</attribute><attribute name="hand_gesture">__undefined__</attribute><attribute name="occlusion">none</attribute><attribute name="nod">__undefined__</attribute></box><box frame="30" keyframe="1" occluded="0" outside="0" xbr="1262.0" xtl="1175.0" ybr="804.0" ytl="552.0"><attribute name="id">0_195_1436b</attribute><attribute name="old_id">pedestrian</attribute><attribute name="look">looking</attribute><attribute name="reaction">__undefined__</attribute><attribute name="action">standing</attribute><attribute name="cross">not-crossing</attribute><attribute name="hand_gesture">__undefined__</attribute><attribute name="occlusion">none</attribute><attribute name="nod">__undefined__</attribute></box><box frame="31" keyframe="1" occluded="0" outside="0" xbr="1271.0" xtl="1183.0" ybr="806.0" ytl="551.0"><attribute name="id">0_195_1436b</attribute><attribute name="old_id">pedestrian</attribute><attribute name="look">looking</attribute><attribute name="reaction">__undefined__</attribute><attribute name="action">standing</attribute><attribute name="cross">not-crossing</attribute><attribute name="hand_gesture">__undefined__</attribute><attribute name="occlusion">none</attribute><attribute name="nod">__undefined__</attribute></box><box frame="32" keyframe="1" occluded="0" outside="0" xbr="1280.0" xtl="1190.0" ybr="811.0" ytl="550.0"><attribute name="id">0_195_1436b</attribute><attribute name="old_id">pedestrian</attribute><attribute name="look">looking</attribute><attribute name="reaction">__undefined__</attribute><attribute name="action">standing</attribute><attribute name="cross">not-crossing</attribute><attribute name="hand_gesture">__undefined__</attribute><attribute name="occlusion">none</attribute><attribute name="nod">__undefined__</attribute></box><box frame="33" keyframe="1" occluded="0" outside="0" xbr="1291.0" xtl="1198.0" ybr="816.0" ytl="550.0"><attribute name="id">0_195_1436b</attribute><attribute name="old_id">pedestrian</attribute><attribute name="look">looking</attribute><attribute name="reaction">__undefined__</attribute><attribute name="action">standing</attribute><attribute name="cross">not-crossing</attribute><attribute name="hand_gesture">__undefined__</attribute><attribute name="occlusion">none</attribute><attribute name="nod">__undefined__</attribute></box><box frame="34" keyframe="1" occluded="0" outside="0" xbr="1300.0" xtl="1205.0" ybr="821.0" ytl="549.0"><attribute name="id">0_195_1436b</attribute><attribute name="old_id">pedestrian</attribute><attribute name="look">looking</attribute><attribute name="reaction">__undefined__</attribute><attribute name="action">standing</attribute><attribute name="cross">not-crossing</attribute><attribute name="hand_gesture">__undefined__</attribute><attribute name="occlusion">none</attribute><attribute name="nod">__undefined__</attribute></box><box frame="35" keyframe="1" occluded="0" outside="0" xbr="1310.0" xtl="1213.0" ybr="828.0" ytl="549.0"><attribute name="id">0_195_1436b</attribute><attribute name="old_id">pedestrian</attribute><attribute name="look">looking</attribute><attribute name="reaction">__undefined__</attribute><attribute name="action">standing</attribute><attribute name="cross">not-crossing</attribute><attribute name="hand_gesture">__undefined__</attribute><attribute name="occlusion">none</attribute><attribute name="nod">__undefined__</attribute></box><box frame="36" keyframe="1" occluded="0" outside="0" xbr="1319.0" xtl="1221.0" ybr="835.0" ytl="549.0"><attribute name="id">0_195_1436b</attribute><attribute name="old_id">pedestrian</attribute><attribute name="look">looking</attribute><attribute name="reaction">__undefined__</attribute><attribute name="action">standing</attribute><attribute name="cross">not-crossing</attribute><attribute name="hand_gesture">__undefined__</attribute><attribute name="occlusion">none</attribute><attribute name="nod">__undefined__</attribute></box><box frame="37" keyframe="1" occluded="0" outside="0" xbr="1329.0" xtl="1229.0" ybr="841.0" ytl="549.0"><attribute name="id">0_195_1436b</attribute><attribute name="old_id">pedestrian</attribute><attribute name="look">looking</attribute><attribute name="reaction">__undefined__</attribute><attribute name="action">standing</attribute><attribute name="cross">not-crossing</attribute><attribute name="hand_gesture">__undefined__</attribute><attribute name="occlusion">none</attribute><attribute name="nod">__undefined__</attribute></box><box frame="38" keyframe="1" occluded="0" outside="0" xbr="1338.0" xtl="1237.0" ybr="848.0" ytl="549.0"><attribute name="id">0_195_1436b</attribute><attribute name="old_id">pedestrian</attribute><attribute name="look">looking</attribute><attribute name="reaction">__undefined__</attribute><attribute name="action">standing</attribute><attribute name="cross">not-crossing</attribute><attribute name="hand_gesture">__undefined__</attribute><attribute name="occlusion">none</attribute><attribute name="nod">__undefined__</attribute></box><box frame="39" keyframe="1" occluded="0" outside="0" xbr="1350.0" xtl="1246.0" ybr="852.0" ytl="550.0"><attribute name="id">0_195_1436b</attribute><attribute name="old_id">pedestrian</attribute><attribute name="look">looking</attribute><attribute name="reaction">__undefined__</attribute><attribute name="action">standing</attribute><attribute name="cross">not-crossing</attribute><attribute name="hand_gesture">__undefined__</attribute><attribute name="occlusion">none</attribute><attribute name="nod">__undefined__</attribute></box><box frame="40" keyframe="1" occluded="0" outside="0" xbr="1362.0" xtl="1254.0" ybr="857.0" ytl="552.0"><attribute name="id">0_195_1436b</attribute><attribute name="old_id">pedestrian</attribute><attribute name="look">looking</attribute><attribute name="reaction">__undefined__</attribute><attribute name="action">standing</attribute><attribute name="cross">not-crossing</attribute><attribute name="hand_gesture">__undefined__</attribute><attribute name="occlusion">none</attribute><attribute name="nod">__undefined__</attribute></box><box frame="41" keyframe="1" occluded="0" outside="0" xbr="1374.0" xtl="1263.0" ybr="861.0" ytl="553.0"><attribute name="id">0_195_1436b</attribute><attribute name="old_id">pedestrian</attribute><attribute name="look">looking</attribute><attribute name="reaction">__undefined__</attribute><attribute name="action">standing</attribute><attribute name="cross">not-crossing</attribute><attribute name="hand_gesture">__undefined__</attribute><attribute name="occlusion">none</attribute><attribute name="nod">__undefined__</attribute></box><box frame="42" keyframe="1" occluded="0" outside="0" xbr="1387.0" xtl="1274.0" ybr="864.0" ytl="550.0"><attribute name="id">0_195_1436b</attribute><attribute name="old_id">pedestrian</attribute><attribute name="look">looking</attribute><attribute name="reaction">__undefined__</attribute><attribute name="action">standing</attribute><attribute name="cross">not-crossing</attribute><attribute name="hand_gesture">__undefined__</attribute><attribute name="occlusion">none</attribute><attribute name="nod">__undefined__</attribute></box><box frame="43" keyframe="1" occluded="0" outside="0" xbr="1401.0" xtl="1285.0" ybr="868.0" ytl="547.0"><attribute name="id">0_195_1436b</attribute><attribute name="old_id">pedestrian</attribute><attribute name="look">looking</attribute><attribute name="reaction">__undefined__</attribute><attribute name="action">standing</attribute><attribute name="cross">not-crossing</attribute><attribute name="hand_gesture">__undefined__</attribute><attribute name="occlusion">none</attribute><attribute name="nod">__undefined__</attribute></box><box frame="44" keyframe="1" occluded="0" outside="0" xbr="1414.0" xtl="1296.0" ybr="871.0" ytl="544.0"><attribute name="id">0_195_1436b</attribute><attribute name="old_id">pedestrian</attribute><attribute name="look">looking</attribute><attribute name="reaction">__undefined__</attribute><attribute name="action">standing</attribute><attribute name="cross">not-crossing</attribute><attribute name="hand_gesture">__undefined__</attribute><attribute name="occlusion">none</attribute><attribute name="nod">__undefined__</attribute></box><box frame="45" keyframe="1" occluded="0" outside="0" xbr="1427.0" xtl="1307.0" ybr="874.0" ytl="541.0"><attribute name="id">0_195_1436b</attribute><attribute name="old_id">pedestrian</attribute><attribute name="look">looking</attribute><attribute name="reaction">__undefined__</attribute><attribute name="action">standing</attribute><attribute name="cross">not-crossing</attribute><attribute name="hand_gesture">__undefined__</attribute><attribute name="occlusion">none</attribute><attribute name="nod">__undefined__</attribute></box><box frame="46" keyframe="1" occluded="0" outside="0" xbr="1444.0" xtl="1319.0" ybr="881.0" ytl="537.0"><attribute name="id">0_195_1436b</attribute><attribute name="old_id">pedestrian</attribute><attribute name="look">looking</attribute><attribute name="reaction">__undefined__</attribute><attribute name="action">standing</attribute><attribute name="cross">not-crossing</attribute><attribute name="hand_gesture">__undefined__</attribute><attribute name="occlusion">none</attribute><attribute name="nod">__undefined__</attribute></box><box frame="47" keyframe="1" occluded="0" outside="0" xbr="1460.0" xtl="1330.0" ybr="888.0" ytl="533.0"><attribute name="id">0_195_1436b</attribute><attribute name="old_id">pedestrian</attribute><attribute name="look">looking</attribute><attribute name="reaction">__undefined__</attribute><attribute name="action">standing</attribute><attribute name="cross">not-crossing</attribute><attribute name="hand_gesture">__undefined__</attribute><attribute name="occlusion">none</attribute><attribute name="nod">__undefined__</attribute></box><box frame="48" keyframe="1" occluded="0" outside="0" xbr="1476.0" xtl="1342.0" ybr="893.0" ytl="528.0"><attribute name="id">0_195_1436b</attribute><attribute name="old_id">pedestrian</attribute><attribute name="look">looking</attribute><attribute name="reaction">__undefined__</attribute><attribute name="action">standing</attribute><attribute name="cross">not-crossing</attribute><attribute name="hand_gesture">__undefined__</attribute><attribute name="occlusion">none</attribute><attribute name="nod">__undefined__</attribute></box><box frame="49" keyframe="1" occluded="0" outside="0" xbr="1492.0" xtl="1353.0" ybr="900.0" ytl="524.0"><attribute name="id">0_195_1436b</attribute><attribute name="old_id">pedestrian</attribute><attribute name="look">looking</attribute><attribute name="reaction">__undefined__</attribute><attribute name="action">standing</attribute><attribute name="cross">not-crossing</attribute><attribute name="hand_gesture">__undefined__</attribute><attribute name="occlusion">none</attribute><attribute name="nod">__undefined__</attribute></box><box frame="50" keyframe="1" occluded="0" outside="0" xbr="1511.0" xtl="1370.0" ybr="906.0" ytl="521.0"><attribute name="id">0_195_1436b</attribute><attribute name="old_id">pedestrian</attribute><attribute name="look">looking</attribute><attribute name="reaction">__undefined__</attribute><attribute name="action">standing</attribute><attribute name="cross">not-crossing</attribute><attribute name="hand_gesture">__undefined__</attribute><attribute name="occlusion">none</attribute><attribute name="nod">__undefined__</attribute></box><box frame="51" keyframe="1" occluded="0" outside="0" xbr="1529.0" xtl="1387.0" ybr="911.0" ytl="518.0"><attribute name="id">0_195_1436b</attribute><attribute name="old_id">pedestrian</attribute><attribute name="look">looking</attribute><attribute name="reaction">__undefined__</attribute><attribute name="action">standing</attribute><attribute name="cross">not-crossing</attribute><attribute name="hand_gesture">__undefined__</attribute><attribute name="occlusion">none</attribute><attribute name="nod">__undefined__</attribute></box><box frame="52" keyframe="1" occluded="0" outside="0" xbr="1547.0" xtl="1403.0" ybr="916.0" ytl="514.0"><attribute name="id">0_195_1436b</attribute><attribute name="old_id">pedestrian</attribute><attribute name="look">looking</attribute><attribute name="reaction">__undefined__</attribute><attribute name="action">standing</attribute><attribute name="cross">not-crossing</attribute><attribute name="hand_gesture">__undefined__</attribute><attribute name="occlusion">none</attribute><attribute name="nod">__undefined__</attribute></box><box frame="53" keyframe="1" occluded="0" outside="0" xbr="1565.0" xtl="1420.0" ybr="921.0" ytl="511.0"><attribute name="id">0_195_1436b</attribute><attribute name="old_id">pedestrian</attribute><attribute name="look">looking</attribute><attribute name="reaction">__undefined__</attribute><attribute name="action">standing</attribute><attribute name="cross">not-crossing</attribute><attribute name="hand_gesture">__undefined__</attribute><attribute name="occlusion">none</attribute><attribute name="nod">__undefined__</attribute></box><box frame="54" keyframe="1" occluded="0" outside="0" xbr="1587.0" xtl="1439.0" ybr="926.0" ytl="510.0"><attribute name="id">0_195_1436b</attribute><attribute name="old_id">pedestrian</attribute><attribute name="look">looking</attribute><attribute name="reaction">__undefined__</attribute><attribute name="action">standing</attribute><attribute name="cross">not-crossing</attribute><attribute name="hand_gesture">__undefined__</attribute><attribute name="occlusion">none</attribute><attribute name="nod">__undefined__</attribute></box><box frame="55" keyframe="1" occluded="0" outside="0" xbr="1610.0" xtl="1458.0" ybr="932.0" ytl="510.0"><attribute name="id">0_195_1436b</attribute><attribute name="old_id">pedestrian</attribute><attribute name="look">looking</attribute><attribute name="reaction">__undefined__</attribute><attribute name="action">standing</attribute><attribute name="cross">not-crossing</attribute><attribute name="hand_gesture">__undefined__</attribute><attribute name="occlusion">none</attribute><attribute name="nod">__undefined__</attribute></box><box frame="56" keyframe="1" occluded="0" outside="0" xbr="1632.0" xtl="1477.0" ybr="948.0" ytl="509.0"><attribute name="id">0_195_1436b</attribute><attribute name="old_id">pedestrian</attribute><attribute name="look">looking</attribute><attribute name="reaction">__undefined__</attribute><attribute name="action">standing</attribute><attribute name="cross">not-crossing</attribute><attribute name="hand_gesture">__undefined__</attribute><attribute name="occlusion">none</attribute><attribute name="nod">__undefined__</attribute></box><box frame="57" keyframe="1" occluded="0" outside="0" xbr="1662.0" xtl="1498.0" ybr="957.0" ytl="510.0"><attribute name="id">0_195_1436b</attribute><attribute name="old_id">pedestrian</attribute><attribute name="look">looking</attribute><attribute name="reaction">__undefined__</attribute><attribute name="action">standing</attribute><attribute name="cross">not-crossing</attribute><attribute name="hand_gesture">__undefined__</attribute><attribute name="occlusion">none</attribute><attribute name="nod">__undefined__</attribute></box><box frame="58" keyframe="1" occluded="0" outside="0" xbr="1691.0" xtl="1521.0" ybr="966.0" ytl="510.0"><attribute name="id">0_195_1436b</attribute><attribute name="old_id">pedestrian</attribute><attribute name="look">looking</attribute><attribute name="reaction">__undefined__</attribute><attribute name="action">standing</attribute><attribute name="cross">not-crossing</attribute><attribute name="hand_gesture">__undefined__</attribute><attribute name="occlusion">none</attribute><attribute name="nod">__undefined__</attribute></box><box frame="59" keyframe="1" occluded="0" outside="0" xbr="1718.0" xtl="1545.0" ybr="972.0" ytl="510.0"><attribute name="id">0_195_1436b</attribute><attribute name="old_id">pedestrian</attribute><attribute name="look">looking</attribute><attribute name="reaction">__undefined__</attribute><attribute name="action">standing</attribute><attribute name="cross">not-crossing</attribute><attribute name="hand_gesture">__undefined__</attribute><attribute name="occlusion">none</attribute><attribute name="nod">__undefined__</attribute></box><box frame="60" keyframe="1" occluded="0" outside="0" xbr="1744.0" xtl="1570.0" ybr="977.0" ytl="510.0"><attribute name="id">0_195_1436b</attribute><attribute name="old_id">pedestrian</attribute><attribute name="look">looking</attribute><attribute name="reaction">__undefined__</attribute><attribute name="action">standing</attribute><attribute name="cross">not-crossing</attribute><attribute name="hand_gesture">__undefined__</attribute><attribute name="occlusion">none</attribute><attribute name="nod">__undefined__</attribute></box><box frame="61" keyframe="1" occluded="0" outside="0" xbr="1771.0" xtl="1596.0" ybr="979.0" ytl="510.0"><attribute name="id">0_195_1436b</attribute><attribute name="old_id">pedestrian</attribute><attribute name="look">looking</attribute><attribute name="reaction">__undefined__</attribute><attribute name="action">standing</attribute><attribute name="cross">not-crossing</attribute><attribute name="hand_gesture">__undefined__</attribute><attribute name="occlusion">none</attribute><attribute name="nod">__undefined__</attribute></box><box frame="62" keyframe="1" occluded="0" outside="0" xbr="1799.0" xtl="1624.0" ybr="989.0" ytl="509.0"><attribute name="id">0_195_1436b</attribute><attribute name="old_id">pedestrian</attribute><attribute name="look">looking</attribute><attribute name="reaction">__undefined__</attribute><attribute name="action">standing</attribute><attribute name="cross">not-crossing</attribute><attribute name="hand_gesture">__undefined__</attribute><attribute name="occlusion">none</attribute><attribute name="nod">__undefined__</attribute></box><box frame="63" keyframe="1" occluded="0" outside="0" xbr="1828.0" xtl="1654.0" ybr="994.0" ytl="507.0"><attribute name="id">0_195_1436b</attribute><attribute name="old_id">pedestrian</attribute><attribute name="look">looking</attribute><attribute name="reaction">__undefined__</attribute><attribute name="action">standing</attribute><attribute name="cross">not-crossing</attribute><attribute name="hand_gesture">__undefined__</attribute><attribute name="occlusion">none</attribute><attribute name="nod">__undefined__</attribute></box><box frame="64" keyframe="1" occluded="0" outside="0" xbr="1858.0" xtl="1684.0" ybr="994.0" ytl="504.0"><attribute name="id">0_195_1436b</attribute><attribute name="old_id">pedestrian</attribute><attribute name="look">looking</attribute><attribute name="reaction">__undefined__</attribute><attribute name="action">standing</attribute><attribute name="cross">not-crossing</attribute><attribute name="hand_gesture">__undefined__</attribute><attribute name="occlusion">none</attribute><attribute name="nod">__undefined__</attribute></box><box frame="65" keyframe="1" occluded="0" outside="0" xbr="1889.0" xtl="1716.0" ybr="993.0" ytl="501.0"><attribute name="id">0_195_1436b</attribute><attribute name="old_id">pedestrian</attribute><attribute name="look">looking</attribute><attribute name="reaction">__undefined__</attribute><attribute name="action">standing</attribute><attribute name="cross">not-crossing</attribute><attribute name="hand_gesture">__undefined__</attribute><attribute name="occlusion">none</attribute><attribute name="nod">__undefined__</attribute></box><box frame="66" keyframe="1" occluded="0" outside="0" xbr="1919.0" xtl="1748.0" ybr="989.0" ytl="497.0"><attribute name="id">0_195_1436b</attribute><attribute name="old_id">pedestrian</attribute><attribute name="look">looking</attribute><attribute name="reaction">__undefined__</attribute><attribute name="action">standing</attribute><attribute name="cross">not-crossing</attribute><attribute name="hand_gesture">__undefined__</attribute><attribute name="occlusion">none</attribute><attribute name="nod">__undefined__</attribute></box><box frame="67" keyframe="1" occluded="0" outside="0" xbr="1919.0" xtl="1784.0" ybr="1006.0" ytl="491.0"><attribute name="id">0_195_1436b</attribute><attribute name="old_id">pedestrian</attribute><attribute name="look">looking</attribute><attribute name="reaction">__undefined__</attribute><attribute name="action">standing</attribute><attribute name="cross">not-crossing</attribute><attribute name="hand_gesture">__undefined__</attribute><attribute name="occlusion">none</attribute><attribute name="nod">__undefined__</attribute></box><box frame="68" keyframe="1" occluded="1" outside="0" xbr="1919.0" xtl="1819.0" ybr="1046.0" ytl="486.0"><attribute name="id">0_195_1436b</attribute><attribute name="old_id">pedestrian</attribute><attribute name="look">looking</attribute><attribute name="reaction">__undefined__</attribute><attribute name="action">standing</attribute><attribute name="cross">not-crossing</attribute><attribute name="hand_gesture">__undefined__</attribute><attribute name="occlusion">part</attribute><attribute name="nod">__undefined__</attribute></box><box frame="69" keyframe="1" occluded="1" outside="0" xbr="1919.0" xtl="1855.0" ybr="1042.0" ytl="480.0"><attribute name="id">0_195_1436b</attribute><attribute name="old_id">pedestrian</attribute><attribute name="look">looking</attribute><attribute name="reaction">__undefined__</attribute><attribute name="action">standing</attribute><attribute name="cross">not-crossing</attribute><attribute name="hand_gesture">__undefined__</attribute><attribute name="occlusion">full</attribute><attribute name="nod">__undefined__</attribute></box></track><track label="ped"><box frame="0" keyframe="1" occluded="1" outside="0" xbr="298.0" xtl="262.0" ybr="682.0" ytl="592.0"><attribute name="id">0_195_1438</attribute><attribute name="old_id">ped3</attribute><attribute name="occlusion">part</attribute></box><box frame="1" keyframe="1" occluded="1" outside="0" xbr="294.0" xtl="258.0" ybr="683.0" ytl="593.0"><attribute name="id">0_195_1438</attribute><attribute name="old_id">ped3</attribute><attribute name="occlusion">part</attribute></box><box frame="2" keyframe="1" occluded="1" outside="0" xbr="290.0" xtl="254.0" ybr="682.0" ytl="593.0"><attribute name="id">0_195_1438</attribute><attribute name="old_id">ped3</attribute><attribute name="occlusion">part</attribute></box><box frame="3" keyframe="1" occluded="1" outside="0" xbr="285.0" xtl="250.0" ybr="682.0" ytl="593.0"><attribute name="id">0_195_1438</attribute><attribute name="old_id">ped3</attribute><attribute name="occlusion">part</attribute></box><box frame="4" keyframe="1" occluded="1" outside="0" xbr="281.0" xtl="246.0" ybr="683.0" ytl="594.0"><attribute name="id">0_195_1438</attribute><attribute name="old_id">ped3</attribute><attribute name="occlusion">part</attribute></box><box frame="5" keyframe="1" occluded="1" outside="0" xbr="278.0" xtl="243.0" ybr="682.0" ytl="594.0"><attribute name="id">0_195_1438</attribute><attribute name="old_id">ped3</attribute><attribute name="occlusion">part</attribute></box><box frame="6" keyframe="1" occluded="1" outside="0" xbr="274.0" xtl="239.0" ybr="682.0" ytl="594.0"><attribute name="id">0_195_1438</attribute><attribute name="old_id">ped3</attribute><attribute name="occlusion">part</attribute></box><box frame="7" keyframe="1" occluded="1" outside="0" xbr="270.0" xtl="235.0" ybr="683.0" ytl="595.0"><attribute name="id">0_195_1438</attribute><attribute name="old_id">ped3</attribute><attribute name="occlusion">part</attribute></box><box frame="8" keyframe="1" occluded="1" outside="0" xbr="266.0" xtl="231.0" ybr="682.0" ytl="595.0"><attribute name="id">0_195_1438</attribute><attribute name="old_id">ped3</attribute><attribute name="occlusion">part</attribute></box><box frame="9" keyframe="1" occluded="1" outside="0" xbr="263.0" xtl="228.0" ybr="682.0" ytl="595.0"><attribute name="id">0_195_1438</attribute><attribute name="old_id">ped3</attribute><attribute name="occlusion">part</attribute></box><box frame="10" keyframe="1" occluded="1" outside="0" xbr="258.0" xtl="224.0" ybr="683.0" ytl="596.0"><attribute name="id">0_195_1438</attribute><attribute name="old_id">ped3</attribute><attribute name="occlusion">part</attribute></box><box frame="11" keyframe="1" occluded="1" outside="0" xbr="254.0" xtl="220.0" ybr="683.0" ytl="596.0"><attribute name="id">0_195_1438</attribute><attribute name="old_id">ped3</attribute><attribute name="occlusion">part</attribute></box><box frame="12" keyframe="1" occluded="1" outside="0" xbr="250.0" xtl="216.0" ybr="682.0" ytl="596.0"><attribute name="id">0_195_1438</attribute><attribute name="old_id">ped3</attribute><attribute name="occlusion">part</attribute></box><box frame="13" keyframe="1" occluded="1" outside="0" xbr="246.0" xtl="212.0" ybr="682.0" ytl="596.0"><attribute name="id">0_195_1438</attribute><attribute name="old_id">ped3</attribute><attribute name="occlusion">part</attribute></box><box frame="14" keyframe="1" occluded="1" outside="0" xbr="243.0" xtl="209.0" ybr="683.0" ytl="597.0"><attribute name="id">0_195_1438</attribute><attribute name="old_id">ped3</attribute><attribute name="occlusion">part</attribute></box><box frame="15" keyframe="1" occluded="1" outside="0" xbr="239.0" xtl="205.0" ybr="682.0" ytl="597.0"><attribute name="id">0_195_1438</attribute><attribute name="old_id">ped3</attribute><attribute name="occlusion">part</attribute></box><box frame="16" keyframe="1" occluded="1" outside="0" xbr="232.0" xtl="198.0" ybr="683.0" ytl="596.0"><attribute name="id">0_195_1438</attribute><attribute name="old_id">ped3</attribute><attribute name="occlusion">part</attribute></box><box frame="17" keyframe="1" occluded="1" outside="0" xbr="227.0" xtl="192.0" ybr="684.0" ytl="595.0"><attribute name="id">0_195_1438</attribute><attribute name="old_id">ped3</attribute><attribute name="occlusion">part</attribute></box><box frame="18" keyframe="1" occluded="1" outside="0" xbr="222.0" xtl="186.0" ybr="685.0" ytl="594.0"><attribute name="id">0_195_1438</attribute><attribute name="old_id">ped3</attribute><attribute name="occlusion">part</attribute></box><box frame="19" keyframe="1" occluded="1" outside="0" xbr="216.0" xtl="180.0" ybr="685.0" ytl="593.0"><attribute name="id">0_195_1438</attribute><attribute name="old_id">ped3</attribute><attribute name="occlusion">part</attribute></box><box frame="20" keyframe="1" occluded="1" outside="0" xbr="210.0" xtl="173.0" ybr="686.0" ytl="592.0"><attribute name="id">0_195_1438</attribute><attribute name="old_id">ped3</attribute><attribute name="occlusion">part</attribute></box><box frame="21" keyframe="1" occluded="1" outside="0" xbr="205.0" xtl="167.0" ybr="687.0" ytl="591.0"><attribute name="id">0_195_1438</attribute><attribute name="old_id">ped3</attribute><attribute name="occlusion">part</attribute></box><box frame="22" keyframe="1" occluded="1" outside="0" xbr="200.0" xtl="161.0" ybr="689.0" ytl="591.0"><attribute name="id">0_195_1438</attribute><attribute name="old_id">ped3</attribute><attribute name="occlusion">part</attribute></box><box frame="23" keyframe="1" occluded="1" outside="0" xbr="193.0" xtl="154.0" ybr="690.0" ytl="590.0"><attribute name="id">0_195_1438</attribute><attribute name="old_id">ped3</attribute><attribute name="occlusion">part</attribute></box><box frame="24" keyframe="1" occluded="1" outside="0" xbr="188.0" xtl="148.0" ybr="690.0" ytl="589.0"><attribute name="id">0_195_1438</attribute><attribute name="old_id">ped3</attribute><attribute name="occlusion">part</attribute></box><box frame="25" keyframe="1" occluded="1" outside="0" xbr="183.0" xtl="142.0" ybr="691.0" ytl="588.0"><attribute name="id">0_195_1438</attribute><attribute name="old_id">ped3</attribute><attribute name="occlusion">part</attribute></box><box frame="26" keyframe="1" occluded="1" outside="0" xbr="176.0" xtl="135.0" ybr="692.0" ytl="587.0"><attribute name="id">0_195_1438</attribute><attribute name="old_id">ped3</attribute><attribute name="occlusion">part</attribute></box><box frame="27" keyframe="1" occluded="1" outside="0" xbr="171.0" xtl="129.0" ybr="693.0" ytl="586.0"><attribute name="id">0_195_1438</attribute><attribute name="old_id">ped3</attribute><attribute name="occlusion">part</attribute></box><box frame="28" keyframe="1" occluded="1" outside="0" xbr="166.0" xtl="123.0" ybr="694.0" ytl="585.0"><attribute name="id">0_195_1438</attribute><attribute name="old_id">ped3</attribute><attribute name="occlusion">part</attribute></box><box frame="29" keyframe="1" occluded="1" outside="0" xbr="160.0" xtl="116.0" ybr="694.0" ytl="584.0"><attribute name="id">0_195_1438</attribute><attribute name="old_id">ped3</attribute><attribute name="occlusion">part</attribute></box><box frame="30" keyframe="1" occluded="1" outside="0" xbr="154.0" xtl="110.0" ybr="695.0" ytl="583.0"><attribute name="id">0_195_1438</attribute><attribute name="old_id">ped3</attribute><attribute name="occlusion">part</attribute></box><box frame="31" keyframe="1" occluded="1" outside="0" xbr="147.0" xtl="103.0" ybr="696.0" ytl="583.0"><attribute name="id">0_195_1438</attribute><attribute name="old_id">ped3</attribute><attribute name="occlusion">part</attribute></box><box frame="32" keyframe="1" occluded="1" outside="0" xbr="140.0" xtl="97.0" ybr="699.0" ytl="582.0"><attribute name="id">0_195_1438</attribute><attribute name="old_id">ped3</attribute><attribute name="occlusion">part</attribute></box><box frame="33" keyframe="1" occluded="1" outside="0" xbr="134.0" xtl="92.0" ybr="701.0" ytl="581.0"><attribute name="id">0_195_1438</attribute><attribute name="old_id">ped3</attribute><attribute name="occlusion">part</attribute></box><box frame="34" keyframe="1" occluded="1" outside="0" xbr="127.0" xtl="86.0" ybr="704.0" ytl="581.0"><attribute name="id">0_195_1438</attribute><attribute name="old_id">ped3</attribute><attribute name="occlusion">part</attribute></box><box frame="35" keyframe="1" occluded="1" outside="0" xbr="120.0" xtl="80.0" ybr="706.0" ytl="580.0"><attribute name="id">0_195_1438</attribute><attribute name="old_id">ped3</attribute><attribute name="occlusion">part</attribute></box><box frame="36" keyframe="1" occluded="1" outside="0" xbr="112.0" xtl="73.0" ybr="708.0" ytl="580.0"><attribute name="id">0_195_1438</attribute><attribute name="old_id">ped3</attribute><attribute name="occlusion">part</attribute></box><box frame="37" keyframe="1" occluded="1" outside="0" xbr="106.0" xtl="67.0" ybr="709.0" ytl="580.0"><attribute name="id">0_195_1438</attribute><attribute name="old_id">ped3</attribute><attribute name="occlusion">part</attribute></box><box frame="38" keyframe="1" occluded="1" outside="0" xbr="98.0" xtl="60.0" ybr="709.0" ytl="579.0"><attribute name="id">0_195_1438</attribute><attribute name="old_id">ped3</attribute><attribute name="occlusion">part</attribute></box><box frame="39" keyframe="1" occluded="1" outside="0" xbr="88.0" xtl="51.0" ybr="709.0" ytl="579.0"><attribute name="id">0_195_1438</attribute><attribute name="old_id">ped3</attribute><attribute name="occlusion">part</attribute></box><box frame="40" keyframe="1" occluded="1" outside="0" xbr="77.0" xtl="40.0" ybr="709.0" ytl="579.0"><attribute name="id">0_195_1438</attribute><attribute name="old_id">ped3</attribute><attribute name="occlusion">part</attribute></box><box frame="41" keyframe="1" occluded="1" outside="0" xbr="65.0" xtl="29.0" ybr="710.0" ytl="579.0"><attribute name="id">0_195_1438</attribute><attribute name="old_id">ped3</attribute><attribute name="occlusion">part</attribute></box><box frame="42" keyframe="1" occluded="1" outside="0" xbr="54.0" xtl="18.0" ybr="709.0" ytl="578.0"><attribute name="id">0_195_1438</attribute><attribute name="old_id">ped3</attribute><attribute name="occlusion">part</attribute></box><box frame="43" keyframe="1" occluded="1" outside="0" xbr="43.0" xtl="8.0" ybr="709.0" ytl="578.0"><attribute name="id">0_195_1438</attribute><attribute name="old_id">ped3</attribute><attribute name="occlusion">part</attribute></box><box frame="44" keyframe="1" occluded="1" outside="0" xbr="37.0" xtl="2.0" ybr="709.0" ytl="578.0"><attribute name="id">0_195_1438</attribute><attribute name="old_id">ped3</attribute><attribute name="occlusion">full</attribute></box><box frame="45" keyframe="1" occluded="1" outside="0" xbr="35.0" xtl="0.0" ybr="709.0" ytl="578.0"><attribute name="id">0_195_1438</attribute><attribute name="old_id">ped3</attribute><attribute name="occlusion">full</attribute></box><box frame="46" keyframe="1" occluded="1" outside="0" xbr="35.0" xtl="0.0" ybr="709.0" ytl="578.0"><attribute name="id">0_195_1438</attribute><attribute name="old_id">ped3</attribute><attribute name="occlusion">full</attribute></box></track><track label="ped"><box frame="59" keyframe="1" occluded="1" outside="0" xbr="653.0" xtl="630.0" ybr="645.0" ytl="601.0"><attribute name="id">0_195_1439</attribute><attribute name="old_id">ped1</attribute><attribute name="occlusion">part</attribute></box><box frame="60" keyframe="1" occluded="1" outside="0" xbr="652.0" xtl="629.0" ybr="646.0" ytl="603.0"><attribute name="id">0_195_1439</attribute><attribute name="old_id">ped1</attribute><attribute name="occlusion">part</attribute></box><box frame="61" keyframe="1" occluded="1" outside="0" xbr="650.0" xtl="627.0" ybr="648.0" ytl="605.0"><attribute name="id">0_195_1439</attribute><attribute name="old_id">ped1</attribute><attribute name="occlusion">part</attribute></box><box frame="62" keyframe="1" occluded="1" outside="0" xbr="649.0" xtl="626.0" ybr="650.0" ytl="607.0"><attribute name="id">0_195_1439</attribute><attribute name="old_id">ped1</attribute><attribute name="occlusion">part</attribute></box><box frame="63" keyframe="1" occluded="1" outside="0" xbr="646.0" xtl="624.0" ybr="650.0" ytl="608.0"><attribute name="id">0_195_1439</attribute><attribute name="old_id">ped1</attribute><attribute name="occlusion">part</attribute></box><box frame="64" keyframe="1" occluded="1" outside="0" xbr="645.0" xtl="623.0" ybr="651.0" ytl="609.0"><attribute name="id">0_195_1439</attribute><attribute name="old_id">ped1</attribute><attribute name="occlusion">part</attribute></box><box frame="65" keyframe="1" occluded="1" outside="0" xbr="644.0" xtl="622.0" ybr="652.0" ytl="610.0"><attribute name="id">0_195_1439</attribute><attribute name="old_id">ped1</attribute><attribute name="occlusion">part</attribute></box><box frame="66" keyframe="1" occluded="1" outside="0" xbr="642.0" xtl="620.0" ybr="651.0" ytl="610.0"><attribute name="id">0_195_1439</attribute><attribute name="old_id">ped1</attribute><attribute name="occlusion">part</attribute></box><box frame="67" keyframe="1" occluded="1" outside="0" xbr="640.0" xtl="619.0" ybr="652.0" ytl="611.0"><attribute name="id">0_195_1439</attribute><attribute name="old_id">ped1</attribute><attribute name="occlusion">part</attribute></box><box frame="68" keyframe="1" occluded="1" outside="0" xbr="638.0" xtl="617.0" ybr="652.0" ytl="611.0"><attribute name="id">0_195_1439</attribute><attribute name="old_id">ped1</attribute><attribute name="occlusion">part</attribute></box><box frame="69" keyframe="1" occluded="1" outside="0" xbr="637.0" xtl="616.0" ybr="652.0" ytl="611.0"><attribute name="id">0_195_1439</attribute><attribute name="old_id">ped1</attribute><attribute name="occlusion">part</attribute></box><box frame="70" keyframe="1" occluded="0" outside="0" xbr="636.0" xtl="615.0" ybr="652.0" ytl="612.0"><attribute name="id">0_195_1439</attribute><attribute name="old_id">ped1</attribute><attribute name="occlusion">none</attribute></box><box frame="71" keyframe="1" occluded="0" outside="0" xbr="634.0" xtl="613.0" ybr="652.0" ytl="612.0"><attribute name="id">0_195_1439</attribute><attribute name="old_id">ped1</attribute><attribute name="occlusion">none</attribute></box><box frame="72" keyframe="1" occluded="0" outside="0" xbr="632.0" xtl="612.0" ybr="652.0" ytl="612.0"><attribute name="id">0_195_1439</attribute><attribute name="old_id">ped1</attribute><attribute name="occlusion">none</attribute></box><box frame="73" keyframe="1" occluded="0" outside="0" xbr="630.0" xtl="610.0" ybr="651.0" ytl="612.0"><attribute name="id">0_195_1439</attribute><attribute name="old_id">ped1</attribute><attribute name="occlusion">none</attribute></box><box frame="74" keyframe="1" occluded="0" outside="0" xbr="629.0" xtl="609.0" ybr="651.0" ytl="612.0"><attribute name="id">0_195_1439</attribute><attribute name="old_id">ped1</attribute><attribute name="occlusion">none</attribute></box><box frame="75" keyframe="1" occluded="0" outside="0" xbr="624.0" xtl="608.0" ybr="651.0" ytl="612.0"><attribute name="id">0_195_1439</attribute><attribute name="old_id">ped1</attribute><attribute name="occlusion">none</attribute></box><box frame="76" keyframe="1" occluded="0" outside="0" xbr="622.0" xtl="606.0" ybr="651.0" ytl="611.0"><attribute name="id">0_195_1439</attribute><attribute name="old_id">ped1</attribute><attribute name="occlusion">none</attribute></box><box frame="77" keyframe="1" occluded="0" outside="0" xbr="619.0" xtl="603.0" ybr="651.0" ytl="611.0"><attribute name="id">0_195_1439</attribute><attribute name="old_id">ped1</attribute><attribute name="occlusion">none</attribute></box><box frame="78" keyframe="1" occluded="0" outside="0" xbr="616.0" xtl="600.0" ybr="650.0" ytl="610.0"><attribute name="id">0_195_1439</attribute><attribute name="old_id">ped1</attribute><attribute name="occlusion">none</attribute></box><box frame="79" keyframe="1" occluded="0" outside="0" xbr="615.0" xtl="598.0" ybr="650.0" ytl="610.0"><attribute name="id">0_195_1439</attribute><attribute name="old_id">ped1</attribute><attribute name="occlusion">none</attribute></box><box frame="80" keyframe="1" occluded="0" outside="0" xbr="612.0" xtl="595.0" ybr="649.0" ytl="609.0"><attribute name="id">0_195_1439</attribute><attribute name="old_id">ped1</attribute><attribute name="occlusion">none</attribute></box><box frame="81" keyframe="1" occluded="0" outside="0" xbr="610.0" xtl="593.0" ybr="648.0" ytl="608.0"><attribute name="id">0_195_1439</attribute><attribute name="old_id">ped1</attribute><attribute name="occlusion">none</attribute></box><box frame="82" keyframe="1" occluded="0" outside="0" xbr="608.0" xtl="591.0" ybr="648.0" ytl="607.0"><attribute name="id">0_195_1439</attribute><attribute name="old_id">ped1</attribute><attribute name="occlusion">none</attribute></box><box frame="83" keyframe="1" occluded="0" outside="0" xbr="606.0" xtl="589.0" ybr="647.0" ytl="606.0"><attribute name="id">0_195_1439</attribute><attribute name="old_id">ped1</attribute><attribute name="occlusion">none</attribute></box><box frame="84" keyframe="1" occluded="0" outside="0" xbr="604.0" xtl="587.0" ybr="648.0" ytl="606.0"><attribute name="id">0_195_1439</attribute><attribute name="old_id">ped1</attribute><attribute name="occlusion">none</attribute></box><box frame="85" keyframe="1" occluded="0" outside="0" xbr="601.0" xtl="584.0" ybr="649.0" ytl="607.0"><attribute name="id">0_195_1439</attribute><attribute name="old_id">ped1</attribute><attribute name="occlusion">none</attribute></box><box frame="86" keyframe="1" occluded="0" outside="0" xbr="599.0" xtl="582.0" ybr="650.0" ytl="607.0"><attribute name="id">0_195_1439</attribute><attribute name="old_id">ped1</attribute><attribute name="occlusion">none</attribute></box><box frame="87" keyframe="1" occluded="0" outside="0" xbr="596.0" xtl="579.0" ybr="650.0" ytl="608.0"><attribute name="id">0_195_1439</attribute><attribute name="old_id">ped1</attribute><attribute name="occlusion">none</attribute></box><box frame="88" keyframe="1" occluded="0" outside="0" xbr="595.0" xtl="577.0" ybr="651.0" ytl="610.0"><attribute name="id">0_195_1439</attribute><attribute name="old_id">ped1</attribute><attribute name="occlusion">none</attribute></box><box frame="89" keyframe="1" occluded="0" outside="0" xbr="592.0" xtl="574.0" ybr="651.0" ytl="611.0"><attribute name="id">0_195_1439</attribute><attribute name="old_id">ped1</attribute><attribute name="occlusion">none</attribute></box></track></annotations>